numap/__init__.py
numap/metrics.py
numap/numap.py
numap/numap_ft.py
numap/utils.py
numap/umap_pytorch/__init__.py
numap/umap_pytorch/data.py
numap/umap_pytorch/main.py
numap/umap_pytorch/model.py
numap/umap_pytorch/modules.py
umap_pytorch/__init__.py
umap_pytorch/data.py
umap_pytorch/main.py
umap_pytorch/model.py
umap_pytorch/modules.py
numap-0.2.3.dist-info/LICENSE.md
numap-0.2.3.dist-info/METADATA
numap-0.2.3.dist-info/WHEEL
numap-0.2.3.dist-info/top_level.txt
numap-0.2.3.dist-info/RECORD
