Metadata-Version: 2.1
Name: numap
Version: 0.2.3
Summary: Generalizable UMAP Implementation
Home-page: https://github.com/TheNirnir/NUMAP
Author: Nir Ben-Ari
Author-email: nirnirba@gmail.com
Classifier: Programming Language :: Python :: 3
Classifier: License :: OSI Approved :: MIT License
Classifier: Operating System :: OS Independent
Requires-Python: >=3.9
License-File: LICENSE.md
Requires-Dist: pytorch-lightning >=2.5.0
Requires-Dist: pynndescent >=0.5.13
Requires-Dist: umap-learn >=0.5.7
Requires-Dist: dill >=0.3.9
Requires-Dist: grease-embeddings >=0.1.1
